fullenrich/__init__.py
fullenrich/client.py
fullenrich/exceptions.py
fullenrich/models.py
fullenrichclient-0.1.0.dist-info/METADATA
fullenrichclient-0.1.0.dist-info/WHEEL
fullenrichclient-0.1.0.dist-info/RECORD
