Metadata-Version: 2.4
Name: fullenrichclient
Version: 0.1.0
Summary: Python client for FullEnrich API - Enrich LinkedIn profiles with contact information
Project-URL: Homepage, https://github.com/ifightcode/Fullenrich-API-Client
Project-URL: Repository, https://github.com/ifightcode/Fullenrich-API-Client
Project-URL: Issues, https://github.com/ifightcode/Fullenrich-API-Client/issues
Author: Tanmoy Sadhukhan
License: MIT
Keywords: contact,email,enrichment,fullenrich,leads,linkedin,phone
Classifier: Development Status :: 4 - Beta
Classifier: Intended Audience :: Developers
Classifier: License :: OSI Approved :: MIT License
Classifier: Programming Language :: Python :: 3
Classifier: Programming Language :: Python :: 3.12
Classifier: Programming Language :: Python :: 3.13
Classifier: Topic :: Software Development :: Libraries :: Python Modules
Requires-Python: >=3.12
Requires-Dist: httpx>=0.27.0
Requires-Dist: python-dotenv>=1.0.0
